lunchable_pushlunch/__about__.py
lunchable_pushlunch/__init__.py
lunchable_pushlunch/base.py
lunchable_pushlunch/cli.py
lunchable_pushlunch/ntfy.py
lunchable_pushlunch/pushover.py
lunchable_pushlunch/py.typed
lunchable_pushlunch-1.4.0.dist-info/METADATA
lunchable_pushlunch-1.4.0.dist-info/WHEEL
lunchable_pushlunch-1.4.0.dist-info/entry_points.txt
lunchable_pushlunch-1.4.0.dist-info/licenses/LICENSE
lunchable_pushlunch-1.4.0.dist-info/RECORD
